wai/__init__.py
wai/alignment.py
wai/basic_dataset.py
wai/camera.py
wai/colmap_parsing_utils.py
wai/compute_colormap.py
wai/core.py
wai/intersection_check.py
wai/io.py
wai/m_ops.py
wai/ops.py
wai/scene_frame.py
wai/semantics.py
wai/colormaps/colors_fps_5k.npz
wai_core-1.0.4.dist-info/METADATA
wai_core-1.0.4.dist-info/WHEEL
wai_core-1.0.4.dist-info/top_level.txt
wai_core-1.0.4.dist-info/RECORD
