Metadata-Version: 2.1
Name: wai-core
Version: 1.0.4
Summary: WAI: World AI format unifying various 3D/4D datasets
Author-email: Norman Mueller <normanm@meta.com>
License: CC-BY-NC-4.0
Requires-Python: >=3.10.0
Requires-Dist: color-science
Requires-Dist: einops
Requires-Dist: imageio
Requires-Dist: iopath
Requires-Dist: matplotlib
Requires-Dist: numpy
Requires-Dist: opencv-python ==4.10.0.84
Requires-Dist: orjson
Requires-Dist: pillow
Requires-Dist: plyfile
Requires-Dist: portalocker
Requires-Dist: pycolmap
Requires-Dist: python-box
Requires-Dist: pyyaml
Requires-Dist: scipy
Requires-Dist: torch
Requires-Dist: torchvision
Requires-Dist: tqdm
Requires-Dist: trimesh
Provides-Extra: dev
Requires-Dist: ruff ; extra == 'dev'
Requires-Dist: pre-commit ; extra == 'dev'
Requires-Dist: pre-commit-hooks ; extra == 'dev'
